Metadata-Version: 1.0
Name: dsdn-distributions-yq
Version: 0.2
Summary: Gaussian and Binomial distributions
Home-page: UNKNOWN
Author: UNKNOWN
Author-email: UNKNOWN
License: UNKNOWN
Platform: UNKNOWN
